src/__init__.py
src/__main__.py
src/config.py
src/tensor_op.py
src/common/__init__.py
src/common/typing.py
src/data_git/__init__.py
src/data_git/csv2jsonl.py
src/data_git/elmo_indexer_with_mask.py
src/data_git/preprocess.py
src/data_git/reader.py
src/data_git/reader_config.py
src/data_git/sparse_adjacency_field.py
src/data_git/utils.py
src/interpret/__init__.py
src/interpret/attention_visualizer.py
src/interpret/show_attention.py
src/models/__init__.py
src/models/graph_nli.py
src/models/syn_nli_model.py
src/modules/__init__.py
src/modules/elmo_token_embedder_with_mask.py
src/modules/graph2graph_encoders/CGConv.py
src/modules/graph2graph_encoders/GATConv.py
src/modules/graph2graph_encoders/HGTConv-cut.py
src/modules/graph2graph_encoders/HGTConv.py
src/modules/graph2graph_encoders/MessagePassing132.py
src/modules/graph2graph_encoders/RGCNConv.py
src/modules/graph2graph_encoders/RGCNConv_msg.py
src/modules/graph2graph_encoders/__init__.py
src/modules/graph2graph_encoders/graph2graph_encoder.py
src/modules/graph2vec_encoders/__init__.py
src/modules/graph2vec_encoders/attention.py
src/modules/graph2vec_encoders/graph2vec_encoder.py
src/modules/graph_pair2graph_pair_encoders/__init__.py
src/modules/graph_pair2graph_pair_encoders/attention_diff.py
src/modules/graph_pair2graph_pair_encoders/graph_pair2graph_pair_encoder.py
src/modules/graph_pair2graph_pair_encoders/graph_pair_mpm.py
src/modules/graph_pair2vec_encoders/__init__.py
src/modules/graph_pair2vec_encoders/graph_embedding_net.py
src/modules/graph_pair2vec_encoders/graph_matching_net.py
src/modules/graph_pair2vec_encoders/graph_pair2vec_encoder.py
src/modules/node_updaters/__init__.py
src/modules/node_updaters/node_updater.py
src/nn/__init__.py
src/predictors/__init__.py
src/predictors/graph_nli_predictor.py
src/predictors/hans_predictor.py
syn_nli-0.0.4.dist-info/LICENSE
syn_nli-0.0.4.dist-info/METADATA
syn_nli-0.0.4.dist-info/WHEEL
syn_nli-0.0.4.dist-info/entry_points.txt
syn_nli-0.0.4.dist-info/top_level.txt
syn_nli-0.0.4.dist-info/RECORD
