Metadata-Version: 2.1
Name: syn-nli
Version: 0.0.4
Summary: package for the paper Syntax Aware Natural Language Inference@<link>
Home-page: https://github.com/EazyReal/2020-IIS-internship
Author: ytlin
Author-email: 0312fs3@gmail.com
License: Apache
Keywords: allennlp NLP deep learning machine
Platform: UNKNOWN
Classifier: Intended Audience :: Science/Research
Classifier: Development Status :: 3 - Alpha
Classifier: License :: OSI Approved :: Apache Software License
Classifier: Programming Language :: Python :: 3.6
Classifier: Topic :: Scientific/Engineering :: Artificial Intelligence
Requires-Python: >=3.6.1
Requires-Dist: torch (<1.7.0,>=1.6.0)
Requires-Dist: torchvision (<0.8.0,>=0.7.0)
Requires-Dist: allennlp (==1.1.0rc3)
Requires-Dist: allennlp-models (==1.1.0rc3)
Requires-Dist: transformers (==3.0.2)
Requires-Dist: torch-geometric (==1.6.0)
Requires-Dist: torch-scatter (==2.0.5)
Requires-Dist: torch-sparse (==0.6.7)
Requires-Dist: tqdm (==4.46.0)
Requires-Dist: typing (==3.7.4.3)
Requires-Dist: pathlib
